docnote-2025.12.4.0.dist-info/METADATA
docnote-2025.12.4.0.dist-info/WHEEL
docnote-2025.12.4.0.dist-info/entry_points.txt
docnote/__init__.py
docnote/py.typed
docnote-2025.12.4.0.dist-info/RECORD
