Metadata-Version: 2.1
Name: docnote
Version: 2025.12.4.0
Summary: A lightweight way of declaring documentation notes as annotations
Requires-Python: >=3.12.0
